{"trial_id": "04", "hyperparameters": {"space": [{"class_name": "Int", "config": {"name": "neurons", "default": null, "conditions": [], "min_value": 32, "max_value": 512, "step": 32, "sampling": "linear"}}, {"class_name": "Choice", "config": {"name": "learning_rate", "default": 0.1, "conditions": [], "values": [0.1, 0.01, 0.15], "ordered": true}}, {"class_name": "Choice", "config": {"name": "batch_size", "default": 4, "conditions": [], "values": [4, 8, 16], "ordered": true}}], "values": {"neurons": 480, "learning_rate": 0.01, "batch_size": 4}}, "metrics": {"metrics": {"loss": {"direction": "min", "observations": [{"value": [2.691896915435791], "step": 0}]}, "accuracy": {"direction": "max", "observations": [{"value": [0.09600000083446503], "step": 0}]}, "val_loss": {"direction": "min", "observations": [{"value": [2.336547374725342], "step": 0}]}, "val_accuracy": {"direction": "max", "observations": [{"value": [0.16200000047683716], "step": 0}]}}}, "score": 0.16200000047683716, "best_step": 0, "status": "COMPLETED", "message": null}